fancybar/__init__.py
fancybar/colors.json
fancybar/progressbar.py
fancybar/spinners.json
fancybar-0.2.0.dist-info/METADATA
fancybar-0.2.0.dist-info/WHEEL
fancybar-0.2.0.dist-info/top_level.txt
fancybar-0.2.0.dist-info/RECORD
