Metadata-Version: 2.1
Name: fancybar
Version: 0.2.0
Summary: A highly customizable terminal progress bar library
Home-page: https://github.com/jenca-adam/fancybar
Author: Adam Jenca
Author-email: jenca.a@gjh.sk
Keywords: Progress bar,TUI
Classifier: Development Status :: 4 - Beta
Classifier: Environment :: Console
Classifier: License :: OSI Approved :: GNU General Public License v2 (GPLv2)
Classifier: Operating System :: OS Independent
Classifier: Programming Language :: Python :: 3.6
Classifier: Programming Language :: Python :: 3.7
Classifier: Programming Language :: Python :: 3.8
Classifier: Programming Language :: Python :: 3.9
Classifier: Programming Language :: Python :: 3.10
Requires-Dist: cursor
Requires-Dist: colored
